source_query_proxy/__init__.py
source_query_proxy/__main__.py
source_query_proxy/cli.py
source_query_proxy/config.py
source_query_proxy/dict_merge.py
source_query_proxy/ebpf_template.py
source_query_proxy/epbf.py
source_query_proxy/logging.py
source_query_proxy/proxy.py
source_query_proxy/source/__init__.py
source_query_proxy/source/messages.py
source_query_proxy/source/util.py
source_query_proxy/stats.py
source_query_proxy/transport.py
source_query_proxy/utils.py
source_query_proxy-2.5.0.dist-info/entry_points.txt
source_query_proxy-2.5.0.dist-info/LICENSE
source_query_proxy-2.5.0.dist-info/WHEEL
source_query_proxy-2.5.0.dist-info/METADATA
source_query_proxy-2.5.0.dist-info/RECORD
