Metadata-Version: 2.1
Name: source-query-proxy
Version: 2.5.0
Summary: Async proxy for Source Engine Query Protocol
Home-page: https://github.com/sqproxy/sqproxy
License: GPL-3.0
Keywords: valve,source,engine,proxy,query,cache
Author: spumer
Author-email: spumer-tm@yandex.ru
Requires-Python: >=3.7,<4.0
Classifier: License :: OSI Approved :: GNU General Public License v3 (GPLv3)
Classifier: Programming Language :: Python :: 3
Classifier: Programming Language :: Python :: 3.7
Classifier: Programming Language :: Python :: 3.8
Classifier: Programming Language :: Python :: 3.9
Classifier: Programming Language :: Python :: 3.10
Classifier: Programming Language :: Python :: 3.11
Requires-Dist: async-timeout (>=3.0,<4.0)
Requires-Dist: asyncio_dgram (>=2.1.0,<3.0.0)
Requires-Dist: backoff (>=2.1.0,<3.0.0)
Requires-Dist: cached-property (>=1.5.2,<2.0.0)
Requires-Dist: click (>=7.0,<8.0)
Requires-Dist: pid (>=2.2,<4.0)
Requires-Dist: pydantic[dotenv] (>=1.4,<2.0)
Requires-Dist: pylru (>=1.2.0,<2.0.0)
Requires-Dist: pyroute2 (>=0.7.5,<0.8.0)
Requires-Dist: python-dotenv (>=0.10.3,<0.15.0)
Requires-Dist: pyyaml (>=6.0,<7.0)
Requires-Dist: sentry-sdk (>1.14.0)
Requires-Dist: uvloop (>=0.16.0)
